order_check_gen/__init__.py
order_check_gen/__main__.py
order_check_gen-0.1.0.dist-info/METADATA
order_check_gen-0.1.0.dist-info/WHEEL
order_check_gen-0.1.0.dist-info/top_level.txt
order_check_gen-0.1.0.dist-info/RECORD
