Metadata-Version: 2.1
Name: order_check_gen
Version: 0.1.0
Author: Plavist Games
